htmlnojs/__init__.py
htmlnojs/core.py
htmlnojs/go_server.ps1
htmlnojs/go_server.py
htmlnojs/htmx_server.py
htmlnojs/instance_registry.py
htmlnojs/port_manager.py
htmlnojs-0.1.0.dist-info/licenses/LICENSE
htmlnojs-0.1.0.dist-info/METADATA
htmlnojs-0.1.0.dist-info/WHEEL
htmlnojs-0.1.0.dist-info/entry_points.txt
htmlnojs-0.1.0.dist-info/top_level.txt
htmlnojs-0.1.0.dist-info/RECORD
