Metadata-Version: 2.4
Name: htmlnojs
Version: 0.1.0
Summary: Async Python orchestrator for HTML-first web applications
Home-page: https://github.com/htmlnojs/python-orchestrator
Author: genderlesspit
Author-email: team@htmlnojs.dev
License: MIT
Project-URL: Homepage, https://htmlnojs.dev
Project-URL: Documentation, https://htmlnojs.dev/docs
Project-URL: Repository, https://github.com/htmlnojs/python-orchestrator
Project-URL: Bug Reports, https://github.com/htmlnojs/python-orchestrator/issues
Keywords: web,htmx,go,async,html-first
Classifier: Development Status :: 3 - Alpha
Classifier: Intended Audience :: Developers
Classifier: License :: OSI Approved :: MIT License
Classifier: Operating System :: OS Independent
Classifier: Programming Language :: Python :: 3
Classifier: Programming Language :: Python :: 3.8
Classifier: Programming Language :: Python :: 3.9
Classifier: Programming Language :: Python :: 3.10
Classifier: Programming Language :: Python :: 3.11
Classifier: Programming Language :: Python :: 3.12
Classifier: Topic :: Internet :: WWW/HTTP :: HTTP Servers
Classifier: Topic :: Software Development :: Libraries :: Python Modules
Classifier: Topic :: Internet :: WWW/HTTP :: Dynamic Content
Requires-Python: >=3.8
License-File: LICENSE
Requires-Dist: fastapi>=0.68.0
Requires-Dist: uvicorn[standard]>=0.15.0
Requires-Dist: aiohttp>=3.8.0
Requires-Dist: loguru>=0.6.0
Requires-Dist: psutil>=5.8.0
Requires-Dist: python-multipart>=0.0.5
Provides-Extra: dev
Requires-Dist: pytest>=6.0; extra == "dev"
Requires-Dist: pytest-asyncio>=0.18.0; extra == "dev"
Requires-Dist: black>=21.0.0; extra == "dev"
Requires-Dist: flake8>=3.9.0; extra == "dev"
Requires-Dist: mypy>=0.910; extra == "dev"
Provides-Extra: docs
Requires-Dist: mkdocs>=1.2.0; extra == "docs"
Requires-Dist: mkdocs-material>=7.0.0; extra == "docs"
Dynamic: author-email
Dynamic: home-page
Dynamic: license-file
Dynamic: requires-python
